[
    {
        "url": "qidian.com",
        "version": 105
    },
    {
        "url": "ruochu.com",
        "version": 100
    },
    {
        "url": "8kana.com",
        "version": 100
    },
    {
        "url": "linovel.net",
        "version": 100
    },
    {
        "url": "heiyan.com",
        "version": 100
    },
    {
        "url": "17k.com",
        "version": 100
    },
    {
        "url": "m.jjwxc.net",
        "version": 100
    },
    {
        "url": "shuqi.com",
        "version": 100
    },
    {
        "url": "gongzicp.com",
        "version": 100
    },
    {
        "url": "ebtang.com",
        "version": 100
    },
    {
        "url": "douban.com",
        "version": 100
    },
    {
        "url": "yousuu.com",
        "version": 100
    }
]