{
    "name": "息壤中文网",
    "url": "xrzww.com",
    "version": 100,
    "search": {
        "url": "https://pre-api.xrzww.com/api/search?type=1&keyword=${key}",
        "list": "$.data.data",
        "name": "$.novel_name",
        "author": "$.novel_author",
        "cover": "http://oss.xrzww.com/${$.novel_cover}", 
        "detail": "https://pre-api.xrzww.com/api/detail?novel_id=${$.novel_id}"
    },
    "detail": {
        "summary":"$.data.novel_info",
        "status": "$.data.",
        "category": "$.data.second_typename",
        "words": "$.data.novel_wordnumber",
        "lastChapter": "$.data.novel_newcname",
        "catalog": "https://pre-api.xrzww.com/api/directoryList?nid=${$.data.novel_id}&orderBy=0"
    },
    "catalog": {
        "list": "$.data.data",
        "name": "$.chapter_name",
        "chapter": "https://pre-api.xrzww.com/api/newRead?nid=${$.chapter_nid}&vid=${$.chapter_vid}&chapter_id=${$.chapter_id}&chapter_order=${$.chapter_order}"
    },
    "chapter": {
        "content": "$.data.content"
    },
    "auth": {
        "login": "https://h5.xrzww.com/#/pages/login/login",
        "cookie": "h5.xrzww.com",
        "verify": "https://pre-api.xrzww.com/api/getUserInfo",
        "logged": "$.message@equal->ok",
        "vip": "$.message@equal->订阅后再阅读",
        "buy": "$.message@equal->ok",
        "profile": "https://h5.xrzww.com/#/pages/mine/index"
    }
}
